Algorithmetn/__init__.py
Algorithmetn/algorithms.py
algorithmetn-0.4.3.dist-info/METADATA
algorithmetn-0.4.3.dist-info/WHEEL
algorithmetn-0.4.3.dist-info/top_level.txt
algorithmetn-0.4.3.dist-info/RECORD
