Metadata-Version: 2.1
Name: algorithmetn
Version: 0.4.3
Summary: A package for basic list operations and algorithms.
Home-page: UNKNOWN
Author: Jaballah Karim
Author-email: lhackerk233@gmail.com
License: MIT
Platform: UNKNOWN
Classifier: Programming Language :: Python :: 3
Classifier: License :: OSI Approved :: MIT License
Classifier: Operating System :: OS Independent
Requires-Python: >=3.6
